simplebot_file2link.py
simplebot_file2link-1.0.0.dist-info/LICENSE
simplebot_file2link-1.0.0.dist-info/METADATA
simplebot_file2link-1.0.0.dist-info/WHEEL
simplebot_file2link-1.0.0.dist-info/entry_points.txt
simplebot_file2link-1.0.0.dist-info/top_level.txt
simplebot_file2link-1.0.0.dist-info/RECORD
